[
  { "entityType": 0, "id": "1", "word": "Vegan", "taboos": ["Essen", "Ern채hrung", "Fleisch", "Vegetarisch", "Milch" ], "index": 1, "difficulty": 1 },
  { "entityType": 0, "id": "2", "word": "Vegetarisch", "taboos": ["Fleisch", "Essen", "Vegan", "Ern채hrung", "Tiere"], "index": 2, "difficulty": 1 },
  { "entityType": 0, "id": "3", "word": "Albedo", "taboos": ["Eis", "Reflexion", "Strahlung", "Energie", "Wolken"], "index": 3, "difficulty": 3 },
  { "entityType": 0, "id": "4", "word": "Temperatur", "taboos": ["W채rme", "K채lte", "Thermometer", "Energie", "Grad"], "index": 4, "difficulty": 1 }
]
